ecoki/__init__.py
ecoki/building_block_folder_names.txt
ecoki/building_block_framework/building_block.py
ecoki/building_block_framework/building_block_executor/building_block_executor.py
ecoki/building_block_framework/building_block_executor/local_building_block_executor.py
ecoki/building_block_framework/building_block_port/building_block_port.py
ecoki/building_block_framework/building_block_port/building_block_port_inlet.py
ecoki/building_block_framework/building_block_port/building_block_port_outlet.py
ecoki/building_block_names.txt
ecoki/building_blocks/code_based/data_integration/acquire_data/data_reader_dataverse/data_reader_dataverse.py
ecoki/building_blocks/code_based/data_integration/acquire_data/data_reader_dataverse/interactive_gui.py
ecoki/building_blocks/code_based/data_integration/acquire_data/data_reader_local/data_reader_local.py
ecoki/building_blocks/code_based/data_integration/acquire_data/data_reader_local/interactive_gui.py
ecoki/building_blocks/code_based/data_integration/acquire_data/data_reader_local/README.md
ecoki/building_blocks/code_based/data_integration/acquire_data/data_reader_lstm/__init__.py
ecoki/building_blocks/code_based/data_integration/acquire_data/data_reader_lstm/data_reader.py
ecoki/building_blocks/code_based/data_integration/acquire_data/data_reader_lstm/interactive_gui.py
ecoki/building_blocks/code_based/data_integration/acquire_data/data_reader_opcua/data_reader_opcua.py
ecoki/building_blocks/code_based/data_integration/acquire_data/data_reader_opcua/opcua_server.py
ecoki/building_blocks/code_based/data_integration/acquire_data/ecoki_data_reader/data_reader_register.py
ecoki/building_blocks/code_based/data_integration/acquire_data/ecoki_data_reader/ecoki_data_reader.py
ecoki/building_blocks/code_based/data_integration/acquire_data/ecoki_data_reader/interactive_gui.py
ecoki/building_blocks/code_based/data_integration/acquire_data/live_data_reader/live_data_visualizer.py
ecoki-0.1.1.dist-info/METADATA
ecoki-0.1.1.dist-info/WHEEL
ecoki-0.1.1.dist-info/RECORD
