Metadata-Version: 2.1
Name: ecoki
Version: 0.1.1
Summary: 
Author: Abhijeet Pendyala
Author-email: Abhijeet.Pendyala@ruhr-uni-bochum.de
Requires-Python: >=3.10,<3.11
Classifier: Programming Language :: Python :: 3
Classifier: Programming Language :: Python :: 3.10
Requires-Dist: dataframe-image (>=0.2.2,<0.3.0)
Requires-Dist: django (>=4.2.1,<4.3.0)
Requires-Dist: django-adminlte3 (>=0.1.6,<0.2.0)
Requires-Dist: django-bootstrap4 (>=23.1,<24.0)
Requires-Dist: django-ckeditor (>=6.5.1,<7.0.0)
Requires-Dist: django-markdownify (>=0.9.3,<0.10.0)
Requires-Dist: django-plotly-dash (>=2.2.0,<3.0.0)
Requires-Dist: django-redis (>=5.2.0,<6.0.0)
Requires-Dist: djangorestframework (>=3.14.0,<4.0.0)
Requires-Dist: dpd-static-support (>=0.0.5,<0.0.6)
Requires-Dist: fastapi (>=0.95.1,<0.96.0)
Requires-Dist: graphviz (>=0.20.1,<0.21.0)
Requires-Dist: httpx (>=0.24.0,<0.25.0)
Requires-Dist: hvplot (>=0.8.3,<0.9.0)
Requires-Dist: matplotlib (>=3.7.1,<4.0.0)
Requires-Dist: networkx (>=3.1,<4.0)
Requires-Dist: numpy (>=1.24.2,<1.25.0)
Requires-Dist: opcua (>=0.98.13,<0.99.0)
Requires-Dist: pandas (>=1.5.3,<1.6.0)
Requires-Dist: panel (>=0.14.4,<0.15.0)
Requires-Dist: param (>=1.9.3,<2.0)
Requires-Dist: pillow (>=9.5.0,<10.0.0)
Requires-Dist: psutil (>=5.9.5,<5.10.0)
Requires-Dist: pydantic (>=1.10.7,<1.11.0)
Requires-Dist: pydataverse (>=0.3.1,<0.4.0)
Requires-Dist: pymongo (>=4.3.3,<5.0.0)
Requires-Dist: pytest (>=7.1.2,<7.2.0)
Requires-Dist: requests (>=2.30.0,<3.0.0)
Requires-Dist: scikit-learn (>=1.2.2,<1.3.0)
Requires-Dist: seaborn (>=0.13.0,<0.14.0)
Requires-Dist: sphinx-copybutton (>=0.5.2,<0.6.0)
Requires-Dist: sphinxcontrib-spelling (>=8.0.0,<9.0.0)
Requires-Dist: tensorflow (>=2.10.0,<2.11.0)
Requires-Dist: tensorflow-io-gcs-filesystem (==0.27.0)
Requires-Dist: textwrap3 (>=0.9.2,<0.10.0)
Requires-Dist: uvicorn (>=0.21.1,<0.22.0)
Requires-Dist: virtualenv (>=20.24.7,<20.25.0)
Requires-Dist: whitenoise (>=6.4.0,<7.0.0)
Requires-Dist: xgboost (>=1.7.5,<1.8.0)
